fastapi_nacos/__init__.py
fastapi_nacos/exception/__init__.py
fastapi_nacos/manager/__init__.py
fastapi_nacos/manager/fastapi_nacos_manager.py
fastapi_nacos/nacos/__init__.py
fastapi_nacos/nacos/nacos_config.py
fastapi_nacos/nacos/nacos_discovery.py
fastapi_nacos/util/__init__.py
fastapi_nacos-0.0.7.dist-info/METADATA
fastapi_nacos-0.0.7.dist-info/WHEEL
fastapi_nacos-0.0.7.dist-info/RECORD
