Metadata-Version: 2.4
Name: fastapi-nacos
Version: 0.0.7
Summary: A FastAPI-friendly integration with Nacos that provides configuration management, service registration and discovery, and client-side load-balanced service calls.
Author-email: ferdinand <gongjpa@gmail.com>
License: MIT
Keywords: aio,config,load balancing,nacos,service discovery,service registry
Classifier: Development Status :: 4 - Beta
Classifier: Framework :: AsyncIO
Classifier: Intended Audience :: Developers
Classifier: License :: OSI Approved :: MIT License
Classifier: Operating System :: OS Independent
Classifier: Programming Language :: Python :: 3
Classifier: Programming Language :: Python :: 3.12
Requires-Python: >=3.12
Requires-Dist: aio-service-caller~=0.1
Requires-Dist: yamlpyconfig[nacos]~=0.1
Provides-Extra: dev
Requires-Dist: aresponses~=3.0; extra == 'dev'
Requires-Dist: black~=25.11; extra == 'dev'
Requires-Dist: mypy~=1.18; extra == 'dev'
Requires-Dist: pytest-asyncio~=1.3; extra == 'dev'
Requires-Dist: pytest-cov~=7.0; extra == 'dev'
Requires-Dist: pytest~=9.0; extra == 'dev'
Requires-Dist: ruff~=0.14; extra == 'dev'
